{
  "$schema": "https://biomejs.dev/schemas/2.3.0/schema.json",
  "vcs": {
    "enabled": true,
    "clientKind": "git",
    "useIgnoreFile": true
  },
  "files": {
    "ignoreUnknown": true
  },
  "formatter": {
    "enabled": true,
    "indentStyle": "space",
    "indentWidth": 2,
    "lineWidth": 80,
    "lineEnding": "lf"
  },
  "linter": {
    "enabled": true,
    "rules": {
      "recommended": true,
      "correctness": {
        "noUnusedVariables": "error",
        "useExhaustiveDependencies": "warn",
        "noUnusedImports": "error"
      },
      "style": {
        "noNonNullAssertion": "off"
      },
      "suspicious": {
        "noExplicitAny": "warn",
        "noShadowRestrictedNames": "off"
      },
      "a11y": {
        "useValidAnchor": "warn",
        "useKeyWithClickEvents": "warn",
        "useSemanticElements": "warn",
        "useAltText": "warn",
        "useAriaPropsSupportedByRole": "warn"
      },
      "performance": {
        "noImgElement": "warn"
      }
    }
  },
  "javascript": {
    "formatter": {
      "quoteStyle": "double",
      "jsxQuoteStyle": "double",
      "semicolons": "always",
      "trailingCommas": "es5"
    }
  }
}
